{
  "name": "origins.neoorigins.feline.name",
  "description": "origins.neoorigins.feline.description",
  "icon": "minecraft:salmon",
  "impact": "medium",
  "order": 10,
  "powers": [
    "neoorigins:feline_no_fall_damage",
    "neoorigins:feline_night_vision",
    "neoorigins:feline_speed_boost",
    "neoorigins:feline_mobs_ignore",
    "neoorigins:feline_active_launch",
    "neoorigins:feline_water_weakness",
    "neoorigins:feline_hunger_drain"
  ],
  "upgrades": [],
  "fur_model": "neoorigins:geo/fur/feline.geo.json",
  "fur_texture": "neoorigins:textures/fur/feline.png",
  "fur_animation": "neoorigins:animations/fur/feline.animation.json"
}
